README.md
setup.py
openidc_client/__init__.py
openidc_client/release.py
openidc_client/requestsauth.py
openidc_client.egg-info/PKG-INFO
openidc_client.egg-info/SOURCES.txt
openidc_client.egg-info/dependency_links.txt
openidc_client.egg-info/requires.txt
openidc_client.egg-info/top_level.txt