Metadata-Version: 1.1
Name: openidc-client
Version: 0.6.0
Summary: OpenID Connect Client with caching and token management
Home-page: https://github.com/puiterwijk/python-openidc-client
Author: Patrick Uiterwijk
Author-email: puiterwijk@fedoraproject.org
License: MIT
Keywords: OpenID Connect Client
Platform: UNKNOWN
Classifier: Development Status :: 4 - Beta
Classifier: Intended Audience :: Developers
Classifier: License :: OSI Approved :: MIT License
Classifier: Programming Language :: Python :: 2.7
Classifier: Topic :: Internet :: WWW/HTTP
Classifier: Topic :: Software Development :: Libraries :: Python Modules
